LICENSE
MANIFEST.in
README.rst
decouple.py
setup.cfg
setup.py
python_decouple_custom.egg-info/PKG-INFO
python_decouple_custom.egg-info/SOURCES.txt
python_decouple_custom.egg-info/dependency_links.txt
python_decouple_custom.egg-info/not-zip-safe
python_decouple_custom.egg-info/top_level.txt