Metadata-Version: 1.1
Name: python-decouple-custom
Version: 3.2
Summary: Strict separation of settings from code.
Home-page: http://github.com/alexseitsinger/python-decouple-custom/
Author: Alex Seitsinger
Author-email: software@alexseitsinger.com
License: MIT
Platform: any
Classifier: Development Status :: 5 - Production/Stable
Classifier: Framework :: Django
Classifier: Framework :: Flask
Classifier: Intended Audience :: Developers
Classifier: License :: OSI Approved :: MIT License
Classifier: Natural Language :: English
Classifier: Operating System :: OS Independent
Classifier: Programming Language :: Python
Classifier: Programming Language :: Python :: 3
Classifier: Topic :: Software Development :: Libraries
